{
  "db_name": "SQLite",
  "query": "\n            SELECT node_id, pm_doc, word_count, char_count, hash, updated_at\n            FROM scene_content\n            ",
  "describe": {
    "columns": [
      {
        "name": "node_id",
        "ordinal": 0,
        "type_info": "Text"
      },
      {
        "name": "pm_doc",
        "ordinal": 1,
        "type_info": "Text"
      },
      {
        "name": "word_count",
        "ordinal": 2,
        "type_info": "Integer"
      },
      {
        "name": "char_count",
        "ordinal": 3,
        "type_info": "Integer"
      },
      {
        "name": "hash",
        "ordinal": 4,
        "type_info": "Text"
      },
      {
        "name": "updated_at",
        "ordinal": 5,
        "type_info": "Text"
      }
    ],
    "parameters": {
      "Right": 0
    },
    "nullable": [
      false,
      false,
      false,
      false,
      false,
      false
    ]
  },
  "hash": "acddc0c439309f660019271751896d8938580e9712a8cb06d61b17823a48ee44"
}
